cloud_base_cli/__init__.py
cloud_base_cli/__main__.py
cloud_base_cli/cli.py
cloud_base_cli/libs/aws.py
cloud_base_cli/libs/gitlab.py
cloud_base_cli/libs/logger.py
cloud_base_cli-0.7.4.dist-info/METADATA
cloud_base_cli-0.7.4.dist-info/WHEEL
cloud_base_cli-0.7.4.dist-info/entry_points.txt
cloud_base_cli-0.7.4.dist-info/RECORD
