Metadata-Version: 2.1
Name: cloud-base-cli
Version: 0.7.4
Summary: Cloud Base ClI App for LZ
Author: Altair Penaredondo
Author-email: apenaredondo@stratpoint.com
Requires-Python: >=3.10,<4.0
Classifier: Programming Language :: Python :: 3
Classifier: Programming Language :: Python :: 3.10
Classifier: Programming Language :: Python :: 3.11
Classifier: Programming Language :: Python :: 3.12
Requires-Dist: boto3 (==1.34.48)
Requires-Dist: click (>=8.1.6,<9.0.0)
Requires-Dist: gitpython (==3.1.42)
Requires-Dist: python-gitlab (==5.3.0)
Requires-Dist: typer (>=0.9.0,<0.10.0)
